LICENSE.md
MANIFEST.in
README.md
pyproject.toml
requirements.txt
setup.cfg
setup.py
src/selenium_driverless/__init__.py
src/selenium_driverless/webdriver.py
src/selenium_driverless.egg-info/PKG-INFO
src/selenium_driverless.egg-info/SOURCES.txt
src/selenium_driverless.egg-info/dependency_links.txt
src/selenium_driverless.egg-info/requires.txt
src/selenium_driverless.egg-info/top_level.txt
src/selenium_driverless/files/__init__.py
src/selenium_driverless/files/js/show_mousemove.js
src/selenium_driverless/files/mv3_extension/driverless_background_mv3_243ffdd55e32a012b4f253b2879af978.js
src/selenium_driverless/files/mv3_extension/manifest.json
src/selenium_driverless/input/__init__.py
src/selenium_driverless/input/pointer.py
src/selenium_driverless/input/utils.py
src/selenium_driverless/scripts/__init__.py
src/selenium_driverless/scripts/driver_utils.py
src/selenium_driverless/scripts/geometry.py
src/selenium_driverless/scripts/network_interceptor.py
src/selenium_driverless/scripts/prefs.py
src/selenium_driverless/scripts/switch_to.py
src/selenium_driverless/sync/__init__.py
src/selenium_driverless/sync/alert.py
src/selenium_driverless/sync/base_target.py
src/selenium_driverless/sync/context.py
src/selenium_driverless/sync/executor.py
src/selenium_driverless/sync/pointer.py
src/selenium_driverless/sync/switch_to.py
src/selenium_driverless/sync/target.py
src/selenium_driverless/sync/webdriver.py
src/selenium_driverless/sync/webelement.py
src/selenium_driverless/types/__init__.py
src/selenium_driverless/types/alert.py
src/selenium_driverless/types/base_target.py
src/selenium_driverless/types/by.py
src/selenium_driverless/types/context.py
src/selenium_driverless/types/deserialize.py
src/selenium_driverless/types/options.py
src/selenium_driverless/types/target.py
src/selenium_driverless/types/webelement.py
src/selenium_driverless/utils/__init__.py
src/selenium_driverless/utils/utils.py