Metadata-Version: 2.1
Name: selenium-driverless
Version: 1.9.4
Summary: Undetected selenium without chromedriver usage (Non-commercial use only!)
Home-page: https://github.com/kaliiiiiiiiii/Selenium-Driverless
Author: Aurin Aegerter
Author-email: aurinliun@gmx.ch
License: https://github.com/kaliiiiiiiiii/Selenium-Driverless/blob/master/LICENSE.md
Project-URL: Documentation, https://github.com/kaliiiiiiiiii/Selenium-Driverless
Project-URL: Bug Reports, https://github.com/kaliiiiiiiiii/Selenium-Driverless/issues
Project-URL: Source Code, https://github.com/kaliiiiiiiiii/Selenium-Driverless
Project-URL: LICENSE, https://github.com/kaliiiiiiiiii/Selenium-Driverless/blob/master/LICENSE.md
Keywords: Selenium,webautomation
Classifier: Development Status :: 2 - Pre-Alpha
Classifier: Intended Audience :: Developers
Classifier: Programming Language :: Python :: 3
Classifier: Programming Language :: Python :: 3.8
Classifier: Programming Language :: Python :: 3.9
Classifier: Programming Language :: Python :: 3.10
Classifier: Programming Language :: Python :: 3.11
Classifier: License :: Free for non-commercial use
Classifier: Natural Language :: English
Classifier: Operating System :: OS Independent
Classifier: Topic :: Internet :: Proxy Servers
Classifier: Topic :: Internet
Classifier: Topic :: Internet :: WWW/HTTP :: Browsers
Requires-Python: >=3.8
License-File: LICENSE.md
Requires-Dist: selenium~=4.6
Requires-Dist: cdp-socket>=1.2.5
Requires-Dist: numpy
Requires-Dist: scipy~=1.7
Requires-Dist: aiofiles
Requires-Dist: platformdirs
Provides-Extra: dev
Requires-Dist: check-manifest; extra == "dev"
